jigu/__init__.py
jigu/__version__.py
jigu/error.py
jigu/listener.py
jigu/client/__init__.py
jigu/client/terra.py
jigu/client/websocket.py
jigu/client/lcd/__init__.py
jigu/client/lcd/lcdclient.py
jigu/client/lcd/lcdrequest.py
jigu/client/lcd/middlewares.py
jigu/client/lcd/api/__init__.py
jigu/client/lcd/api/tendermint.py
jigu/client/lcd/api/tx.py
jigu/client/lcd/api/modules/__init__.py
jigu/client/lcd/api/modules/auth.py
jigu/client/lcd/api/modules/bank.py
jigu/client/lcd/api/modules/distribution.py
jigu/client/lcd/api/modules/gov.py
jigu/client/lcd/api/modules/market.py
jigu/client/lcd/api/modules/oracle.py
jigu/client/lcd/api/modules/slashing.py
jigu/client/lcd/api/modules/staking.py
jigu/client/lcd/api/modules/supply.py
jigu/client/lcd/api/modules/treasury.py
jigu/client/object_query/__init__.py
jigu/client/object_query/account.py
jigu/client/object_query/blocks.py
jigu/client/object_query/denom.py
jigu/client/object_query/proposal.py
jigu/client/object_query/validator.py
jigu/client/object_query/wallet.py
jigu/core/__init__.py
jigu/core/bank.py
jigu/core/block.py
jigu/core/denoms.py
jigu/core/event.py
jigu/core/oracle.py
jigu/core/treasury.py
jigu/core/auth/__init__.py
jigu/core/auth/account.py
jigu/core/auth/transaction.py
jigu/core/msg/__init__.py
jigu/core/msg/bank.py
jigu/core/msg/distribution.py
jigu/core/msg/gov.py
jigu/core/msg/market.py
jigu/core/msg/oracle.py
jigu/core/msg/slashing.py
jigu/core/msg/staking.py
jigu/core/proposal/__init__.py
jigu/core/proposal/distribution.py
jigu/core/proposal/gov.py
jigu/core/proposal/params.py
jigu/core/proposal/treasury.py
jigu/core/sdk/__init__.py
jigu/core/sdk/address.py
jigu/core/sdk/coin.py
jigu/core/sdk/dec.py
jigu/core/sdk/pubkey.py
jigu/core/sdk/timestamp.py
jigu/core/staking/__init__.py
jigu/core/staking/delegation.py
jigu/core/staking/validator.py
jigu/key/__init__.py
jigu/key/mnemonic.py
jigu/query/__init__.py
jigu/query/event.py
jigu/query/msginfo.py
jigu/query/txinfo.py
jigu/transform/__init__.py
jigu-0.1.4.dist-info/LICENSE
jigu-0.1.4.dist-info/METADATA
jigu-0.1.4.dist-info/WHEEL
jigu-0.1.4.dist-info/top_level.txt
jigu-0.1.4.dist-info/RECORD
