Metadata-Version: 2.1
Name: jigu
Version: 0.1.4
Summary: Python SDK for Terra
Home-page: https://jigu.terra.money/
Author: Terraform Labs, PTE. LTD
Author-email: engineering@terra.money
License: MIT
Keywords: terra jigu sdk blockchain defi finance
Platform: UNKNOWN
Classifier: Development Status :: 2 - Pre-Alpha
Classifier: Intended Audience :: Developers
Classifier: License :: OSI Approved :: MIT License
Classifier: Natural Language :: English
Classifier: Programming Language :: Python :: 3
Classifier: Programming Language :: Python :: 3.7
Classifier: Programming Language :: Python :: 3.8
Requires-Python: >=3.7
Requires-Dist: bip32utils (~=0.3.0)
Requires-Dist: mnemonic (~=0.18.0)
Requires-Dist: bech32 (~=1.1)
Requires-Dist: ecdsa (~=0.13.2)
Requires-Dist: requests (~=2.22)
Requires-Dist: requests-futures (~=1.0.0)
Requires-Dist: wrapt (~=1.11.2)
Requires-Dist: python-dateutil (~=2.8.1)
Requires-Dist: pygments (~=2.5.2)
Requires-Dist: cached-property (~=1.5.1)
Requires-Dist: fastjsonschema (~=2.14.2)
Requires-Dist: tabulate (~=0.8.6)
Requires-Dist: python-box (~=4.0.4)
Requires-Dist: websockets (~=8.1)
Requires-Dist: toolz (~=0.10.0)
Requires-Dist: bidict (~=0.19.0)
